charticulator/__init__.py
charticulator/frontend/config.js
charticulator/frontend/index.html
charticulator/frontend/main.js
charticulator/frontend/streamlit-component-lib.js
charticulator/frontend/style.css
charticulator/frontend/charticulator/dist/about.html
charticulator/frontend/charticulator/dist/favicon.ico
charticulator/frontend/charticulator/dist/index.html
charticulator/frontend/charticulator/dist/data/THIRD_PARTY.json
charticulator/frontend/charticulator/dist/data/config.js
charticulator/frontend/charticulator/dist/scripts/about.bundle.js
charticulator/frontend/charticulator/dist/scripts/about.d.ts
charticulator/frontend/charticulator/dist/scripts/about.js
charticulator/frontend/charticulator/dist/scripts/about.js.map
charticulator/frontend/charticulator/dist/scripts/app.bundle.d.ts
charticulator/frontend/charticulator/dist/scripts/app.bundle.js
charticulator/frontend/charticulator/dist/scripts/config.json
charticulator/frontend/charticulator/dist/scripts/container.bundle.d.ts
charticulator/frontend/charticulator/dist/scripts/container.bundle.js
charticulator/frontend/charticulator/dist/scripts/index.d.ts
charticulator/frontend/charticulator/dist/scripts/index.js
charticulator/frontend/charticulator/dist/scripts/index.js.map
charticulator/frontend/charticulator/dist/scripts/strings.d.ts
charticulator/frontend/charticulator/dist/scripts/strings.js
charticulator/frontend/charticulator/dist/scripts/strings.js.map
charticulator/frontend/charticulator/dist/scripts/worker.bundle.js
charticulator/frontend/charticulator/dist/scripts/app/application.d.ts
charticulator/frontend/charticulator/dist/scripts/app/application.js
charticulator/frontend/charticulator/dist/scripts/app/application.js.map
charticulator/frontend/charticulator/dist/scripts/app/config.d.ts
charticulator/frontend/charticulator/dist/scripts/app/config.js
charticulator/frontend/charticulator/dist/scripts/app/config.js.map
charticulator/frontend/charticulator/dist/scripts/app/context_component.d.ts
streamlit_charticulator-0.0.7.dist-info/LICENSE
streamlit_charticulator-0.0.7.dist-info/METADATA
streamlit_charticulator-0.0.7.dist-info/WHEEL
streamlit_charticulator-0.0.7.dist-info/top_level.txt
streamlit_charticulator-0.0.7.dist-info/RECORD
