Metadata-Version: 2.1
Name: streamlit-charticulator
Version: 0.0.7
Summary: Component to render charticulator templates with streamlit data
Author: Ilfat Galiev
Author-email: zbritva@gmail.com
Requires-Python: >=3.7
License-File: LICENSE
Requires-Dist: streamlit (>=1.2)
Requires-Dist: jinja2
